ciara_python/__init__.py
ciara_python/ciara.py
ciara_python/get_background_full.py
ciara_python-1.0.4.dist-info/LICENSE
ciara_python-1.0.4.dist-info/METADATA
ciara_python-1.0.4.dist-info/WHEEL
ciara_python-1.0.4.dist-info/top_level.txt
ciara_python-1.0.4.dist-info/RECORD
