Metadata-Version: 2.1
Name: ciara-python
Version: 1.0.4
Summary: "Cluster Independent Algorithm for the identification of RAre cell types."
Home-page: https://github.com/ScialdoneLab/CIARA_python
Author: Marco Stock
Author-email: marco.stock@tum.de
License: MIT
Platform: UNKNOWN
Requires-Python: >=3.8
License-File: LICENSE
Requires-Dist: scanpy
